springer/__init__.py
springer/__main__.py
springer/__version__.py
springer/catalog.py
springer/constants.py
springer/urls.py
springer-0.17.0.dist-info/entry_points.txt
springer-0.17.0.dist-info/LICENSE
springer-0.17.0.dist-info/WHEEL
springer-0.17.0.dist-info/METADATA
springer-0.17.0.dist-info/RECORD
