Metadata-Version: 2.1
Name: springer
Version: 0.17.0
Summary: Bulk Springer Textbook Downloader
Home-page: http://github.com/JnyJny/springer_downloader
License: Apache-2.0
Author: JnyJny
Author-email: erik.oshaughnessy@gmail.com
Requires-Python: >=3.7,<4.0
Classifier: License :: OSI Approved :: Apache Software License
Classifier: Programming Language :: Python :: 3
Classifier: Programming Language :: Python :: 3.7
Classifier: Programming Language :: Python :: 3.8
Requires-Dist: loguru (>=0.4.1,<0.5.0)
Requires-Dist: pandas (>=1.0.3,<2.0.0)
Requires-Dist: requests (>=2.23.0,<3.0.0)
Requires-Dist: toml (>=0.10.0,<0.11.0)
Requires-Dist: typer (>=0.1.1,<0.2.0)
Requires-Dist: xlrd (>=1.2.0,<2.0.0)
Project-URL: Repository, http://github.com/JnyJny/springer_downloader
